simple_signal_handler/__init__.py
simple_signal_handler/_simple_signal_handler.py
simple_signal_handler-0.1.dist-info/DESCRIPTION.rst
simple_signal_handler-0.1.dist-info/METADATA
simple_signal_handler-0.1.dist-info/RECORD
simple_signal_handler-0.1.dist-info/WHEEL
simple_signal_handler-0.1.dist-info/metadata.json
simple_signal_handler-0.1.dist-info/top_level.txt
