Metadata-Version: 2.0
Name: simple-signal-handler
Version: 0.1
Summary: A simple handler for signals in Python.
Home-page: https://github.com/timkittel/simple-signal-handler
Author: Tim Kittel
Author-email: Tim.Kittel@pik-potsdam.de
License: BSD-2-clause
Keywords: signal-handling
Platform: UNKNOWN
Classifier: Development Status :: 3 - Alpha
Classifier: Intended Audience :: Developers
Classifier: Intended Audience :: Science/Research
Classifier: Topic :: Software Development
Classifier: License :: OSI Approved :: MIT License
Classifier: Programming Language :: Python :: 2
Classifier: Programming Language :: Python :: 2.6
Classifier: Programming Language :: Python :: 2.7
Classifier: Programming Language :: Python :: 3
Classifier: Programming Language :: Python :: 3.2
Classifier: Programming Language :: Python :: 3.3
Classifier: Programming Language :: Python :: 3.4
Classifier: Programming Language :: Python :: 3.5
Classifier: Programming Language :: Python :: 3.6
